barcodactyl/cli.py
barcodactyl/detector.py
barcodactyl/io_fastq.py
barcodactyl/io_sam_bam.py
barcodactyl/typing.py
barcodactyl-0.1.3.dist-info/licenses/LICENSE
barcodactyl-0.1.3.dist-info/METADATA
barcodactyl-0.1.3.dist-info/WHEEL
barcodactyl-0.1.3.dist-info/entry_points.txt
barcodactyl-0.1.3.dist-info/top_level.txt
barcodactyl-0.1.3.dist-info/RECORD
