Metadata-Version: 2.4
Name: barcodactyl
Version: 0.1.3
Summary: Split barcoded reads into per-barcode files (FASTQ/SAM/BAM).
Author-email: Theerayut <theerayut_aeiw_123@hotmail.com>
License: MIT
Project-URL: Homepage, https://aeiwz.github.io/barcodactyl
Requires-Python: >=3.8
License-File: LICENSE
Requires-Dist: pysam>=0.22.0
Dynamic: license-file
